rufus_scraper/__init__.py
rufus_scraper/rufus_scraper.py
rufus_scraper-1.0.1.dist-info/METADATA
rufus_scraper-1.0.1.dist-info/WHEEL
rufus_scraper-1.0.1.dist-info/top_level.txt
rufus_scraper-1.0.1.dist-info/RECORD
