Metadata-Version: 2.1
Name: rufus-scraper
Version: 1.0.1
Summary: A smart web scraper powered by OpenAI for relevance-based content extraction.
Home-page: https://github.com/gdevakumar/Rufus-Scraper
Author: Deva Kumar Gajulamandyam
Author-email: gdevakumar267@gmail.com
Classifier: Programming Language :: Python :: 3
Classifier: License :: OSI Approved :: MIT License
Classifier: Operating System :: OS Independent
Requires-Python: >=3.9
Requires-Dist: requests
Requires-Dist: beautifulsoup4
Requires-Dist: markdownify
Requires-Dist: openai
